muc_lookup.py
wes.py
wesng-1.0.3.dist-info/LICENSE.txt
wesng-1.0.3.dist-info/METADATA
wesng-1.0.3.dist-info/WHEEL
wesng-1.0.3.dist-info/entry_points.txt
wesng-1.0.3.dist-info/top_level.txt
wesng-1.0.3.dist-info/RECORD
